{
  "annotations": {
    "list": [
      {
        "builtIn": 1,
        "datasource": {
          "type": "grafana",
          "uid": "-- Grafana --"
        },
        "enable": true,
        "hide": true,
        "iconColor": "rgba(0, 211, 255, 1)",
        "name": "Annotations & Alerts",
        "target": {
          "limit": 100,
          "matchAny": false,
          "tags": [],
          "type": "dashboard"
        },
        "type": "dashboard"
      }
    ]
  },
  "editable": true,
  "fiscalYearStartMonth": 0,
  "graphTooltip": 0,
  "links": [],
  "liveNow": false,
  "panels": [
    {
      "datasource": {
        "type": "loki",
        "uid": "loki-micro-service"
      },
      "gridPos": {
        "h": 8,
        "w": 12,
        "x": 0,
        "y": 0
      },
      "id": 11,
      "options": {
        "dedupStrategy": "none",
        "enableLogDetails": true,
        "prettifyLogMessage": true,
        "showCommonLabels": true,
        "showLabels": false,
        "showTime": true,
        "sortOrder": "Descending",
        "wrapLogMessage": true
      },
      "targets": [
        {
          "datasource": {
            "type": "loki",
            "uid": "loki-micro-service"
          },
          "editorMode": "builder",
          "expr": "{container=\"payment-service\"} |= ``",
          "queryType": "range",
          "refId": "A"
        }
      ],
      "title": "PAYMENT-SERVICE-LOGS",
      "transparent": true,
      "type": "logs"
    },
    {
      "datasource": {
        "type": "loki",
        "uid": "loki-micro-service"
      },
      "gridPos": {
        "h": 8,
        "w": 12,
        "x": 12,
        "y": 0
      },
      "id": 8,
      "options": {
        "dedupStrategy": "none",
        "enableLogDetails": true,
        "prettifyLogMessage": true,
        "showCommonLabels": true,
        "showLabels": true,
        "showTime": true,
        "sortOrder": "Descending",
        "wrapLogMessage": true
      },
      "targets": [
        {
          "datasource": {
            "type": "loki",
            "uid": "loki-micro-service"
          },
          "editorMode": "builder",
          "expr": "{container=\"catalog-service\"} |= ``",
          "queryType": "range",
          "refId": "A"
        }
      ],
      "title": "CATALOG-SERVICE-LOGS",
      "type": "logs"
    },
    {
      "datasource": {
        "type": "loki",
        "uid": "loki-micro-service"
      },
      "gridPos": {
        "h": 8,
        "w": 12,
        "x": 0,
        "y": 8
      },
      "id": 10,
      "options": {
        "dedupStrategy": "none",
        "enableLogDetails": true,
        "prettifyLogMessage": true,
        "showCommonLabels": true,
        "showLabels": false,
        "showTime": true,
        "sortOrder": "Descending",
        "wrapLogMessage": true
      },
      "targets": [
        {
          "datasource": {
            "type": "loki",
            "uid": "loki-micro-service"
          },
          "editorMode": "builder",
          "expr": "{container=\"order-service\"} |= ``",
          "queryType": "range",
          "refId": "A"
        }
      ],
      "title": "ORDER-SERVICE-LOGS",
      "transparent": true,
      "type": "logs"
    },
    {
      "datasource": {
        "type": "loki",
        "uid": "loki-micro-service"
      },
      "gridPos": {
        "h": 8,
        "w": 12,
        "x": 12,
        "y": 8
      },
      "id": 7,
      "options": {
        "dedupStrategy": "none",
        "enableLogDetails": true,
        "prettifyLogMessage": true,
        "showCommonLabels": true,
        "showLabels": true,
        "showTime": true,
        "sortOrder": "Descending",
        "wrapLogMessage": true
      },
      "targets": [
        {
          "datasource": {
            "type": "loki",
            "uid": "loki-micro-service"
          },
          "editorMode": "builder",
          "expr": "{container=\"api-gateway\"} |= ``",
          "queryType": "range",
          "refId": "A"
        }
      ],
      "title": "API-GATEWAY-LOGS",
      "transparent": true,
      "type": "logs"
    },
    {
      "datasource": {
        "type": "loki",
        "uid": "loki-micro-service"
      },
      "gridPos": {
        "h": 8,
        "w": 12,
        "x": 0,
        "y": 16
      },
      "id": 9,
      "options": {
        "dedupStrategy": "none",
        "enableLogDetails": true,
        "prettifyLogMessage": true,
        "showCommonLabels": true,
        "showLabels": false,
        "showTime": true,
        "sortOrder": "Descending",
        "wrapLogMessage": true
      },
      "targets": [
        {
          "datasource": {
            "type": "loki",
            "uid": "loki-micro-service"
          },
          "editorMode": "builder",
          "expr": "{container=\"inventory-service\"} |= ``",
          "queryType": "range",
          "refId": "A"
        }
      ],
      "title": "INVENTORY-SERVICE-LOGS",
      "type": "logs"
    },
    {
      "datasource": {
        "type": "loki",
        "uid": "loki-micro-service"
      },
      "gridPos": {
        "h": 8,
        "w": 12,
        "x": 12,
        "y": 16
      },
      "id": 12,
      "options": {
        "dedupStrategy": "none",
        "enableLogDetails": true,
        "prettifyLogMessage": true,
        "showCommonLabels": true,
        "showLabels": false,
        "showTime": true,
        "sortOrder": "Descending",
        "wrapLogMessage": true
      },
      "targets": [
        {
          "datasource": {
            "type": "loki",
            "uid": "loki-micro-service"
          },
          "editorMode": "builder",
          "expr": "{container=\"config-server\"} |= ``",
          "queryType": "range",
          "refId": "A"
        }
      ],
      "title": "CONFIG-SERVER-LOGS",
      "transparent": true,
      "type": "logs"
    },
    {
      "datasource": {
        "type": "prometheus",
        "uid": "prometheus-micro-service"
      },
      "fieldConfig": {
        "defaults": {
          "color": {
            "mode": "palette-classic"
          },
          "custom": {
            "axisCenteredZero": false,
            "axisColorMode": "text",
            "axisLabel": "",
            "axisPlacement": "auto",
            "barAlignment": 0,
            "drawStyle": "line",
            "fillOpacity": 0,
            "gradientMode": "none",
            "hideFrom": {
              "legend": false,
              "tooltip": false,
              "viz": false
            },
            "insertNulls": false,
            "lineInterpolation": "linear",
            "lineWidth": 1,
            "pointSize": 5,
            "scaleDistribution": {
              "type": "linear"
            },
            "showPoints": "auto",
            "spanNulls": false,
            "stacking": {
              "group": "A",
              "mode": "none"
            },
            "thresholdsStyle": {
              "mode": "off"
            }
          },
          "mappings": [],
          "thresholds": {
            "mode": "absolute",
            "steps": [
              {
                "color": "green",
                "value": null
              },
              {
                "color": "red",
                "value": 80
              }
            ]
          },
          "unit": "s"
        },
        "overrides": []
      },
      "gridPos": {
        "h": 10,
        "w": 23,
        "x": 0,
        "y": 24
      },
      "id": 4,
      "options": {
        "legend": {
          "calcs": [],
          "displayMode": "list",
          "placement": "bottom",
          "showLegend": true
        },
        "tooltip": {
          "mode": "single",
          "sort": "none"
        }
      },
      "targets": [
        {
          "datasource": {
            "type": "prometheus",
            "uid": "prometheus-micro-service"
          },
          "editorMode": "code",
          "exemplar": true,
          "expr": "histogram_quantile(1.00, sum(rate(http_server_requests_seconds_bucket{uri=~\".*\"}[$__rate_interval])) by (le))",
          "legendFormat": "max",
          "range": true,
          "refId": "A"
        },
        {
          "datasource": {
            "type": "prometheus",
            "uid": "prometheus-micro-service"
          },
          "editorMode": "code",
          "exemplar": true,
          "expr": "histogram_quantile(0.99, sum(rate(http_server_requests_seconds_bucket{uri=~\".*\"}[$__rate_interval])) by (le))",
          "hide": false,
          "legendFormat": "tp99",
          "range": true,
          "refId": "B"
        },
        {
          "datasource": {
            "type": "prometheus",
            "uid": "prometheus-micro-service"
          },
          "editorMode": "code",
          "exemplar": true,
          "expr": "histogram_quantile(0.95, sum(rate(http_server_requests_seconds_bucket{uri=~\".*\"}[$__rate_interval])) by (le))",
          "hide": false,
          "legendFormat": "tp95",
          "range": true,
          "refId": "C"
        }
      ],
      "title": "latency for All",
      "type": "timeseries"
    }
  ],
  "refresh": "auto",
  "schemaVersion": 38,
  "style": "dark",
  "tags": [],
  "templating": {
    "list": []
  },
  "time": {
    "from": "now-15m",
    "to": "now"
  },
  "timepicker": {},
  "timezone": "",
  "title": "Logs, Traces, Metrics",
  "uid": "szVLMe97z",
  "version": 1,
  "weekStart": ""
}